Workbook

Sheet Sales Data
A1: Date | B1: Product | C1: Quantity Sold | D1: Unit Price | E1: Total Cost | F1: Deposit Paid | G1: Balance
E2: =C2*D2 | G2: =E2-F2
E3: =C3*D3 | G3: =E3-F3
E4: =C4*D4 | G4: =E4-F4
E5: =C5*D5 | G5: =E5-F5
E6: =C6*D6 | G6: =E6-F6
E7: =C7*D7 | G7: =E7-F7
E8: =C8*D8 | G8: =E8-F8
E9: =C9*D9 | G9: =E9-F9
E10: =C10*D10 | G10: =E10-F10
E11: =C11*D11 | G11: =E11-F11
E12: =C12*D12 | G12: =E12-F12
E13: =C13*D13 | G13: =E13-F13
... E200: =C200*D200 | G200: =E200-F200

Sheet Stock
A1: Product | B1: Opening Stock | C1: Stock In | D1: Stock Out (Auto) | E1: Remaining Stock
D2: =SUMIF('Sales Data'!B:B,A2,'Sales Data'!C:C) | E2: =B2+C2-D2
D3: =SUMIF('Sales Data'!B:B,A3,'Sales Data'!C:C) | E3: =B3+C3-D3
D4: =SUMIF('Sales Data'!B:B,A4,'Sales Data'!C:C) | E4: =B4+C4-D4
D5: =SUMIF('Sales Data'!B:B,A5,'Sales Data'!C:C) | E5: =B5+C5-D5
D6: =SUMIF('Sales Data'!B:B,A6,'Sales Data'!C:C) | E6: =B6+C6-D6
D7: =SUMIF('Sales Data'!B:B,A7,'Sales Data'!C:C) | E7: =B7+C7-D7
D8: =SUMIF('Sales Data'!B:B,A8,'Sales Data'!C:C) | E8: =B8+C8-D8
D9: =SUMIF('Sales Data'!B:B,A9,'Sales Data'!C:C) | E9: =B9+C9-D9
D10: =SUMIF('Sales Data'!B:B,A10,'Sales Data'!C:C) | E10: =B10+C10-D10
D11: =SUMIF('Sales Data'!B:B,A11,'Sales Data'!C:C) | E11: =B11+C11-D11
D12: =SUMIF('Sales Data'!B:B,A12,'Sales Data'!C:C) | E12: =B12+C12-D12
D13: =SUMIF('Sales Data'!B:B,A13,'Sales Data'!C:C) | E13: =B13+C13-D13
... D100: =SUMIF('Sales Data'!B:B,A100,'Sales Data'!C:C) | E100: =B100+C100-D100

Sheet Dashboard
A1: BUSINESS DASHBOARD
A3: Total Sales | B3: =SUM('Sales Data'!E2:E200)
A4: Total Deposits | B4: =SUM('Sales Data'!F2:F200)
A5: Total Balance Owed | B5: =SUM('Sales Data'!G2:G200)
A6: Total Stock Remaining | B6: =SUM(Stock!E2:E100)
